{
  "title": "Circuits 1",
  "description": "Introduction to analog electrical systems with emphasis on audio circuits and signals. Covers fundamental laws, reactive components, AC analysis, op-amps, filters, and Fourier series.",
  "creator": "Dan McCreary",
  "date": "2026-01-30",
  "version": "1.0",
  "format": "Learning Graph JSON v1.0",
  "schema": "https://raw.githubusercontent.com/dmccreary/learning-graphs/refs/heads/main/src/schema/learning-graph-schema.json",
  "license": "CC BY-NC-SA 4.0 DEED"
}
